strrange/__init__.py
strrange/alphabet.py
strrange/concat.py
strrange/gen.py
strrange/pattern.py
strrange/util.py
strrange-0.1.dist-info/licenses/LICENSE
strrange-0.1.dist-info/WHEEL
strrange-0.1.dist-info/METADATA
strrange-0.1.dist-info/RECORD
