Metadata-Version: 2.4
Name: strrange
Version: 0.1
Summary: Generate inclusive lexicographic ranges of strings
Author-email: Oleh Alistratov <alistratov.dev@gmail.com>
Requires-Python: >=3.10
Classifier: Development Status :: 3 - Alpha
Classifier: Programming Language :: Python :: 3
Classifier: License :: OSI Approved :: Apache Software License
Classifier: Operating System :: OS Independent
License-File: LICENSE
Project-URL: Documentation, https://bit-permutation.readthedocs.io/en/latest/
Project-URL: Homepage, https://github.com/alistratov/bit-permutation
Project-URL: Issues, https://github.com/alistratov/bit-permutation/issues
